src/rasterize.sv
`timescale 1ns / 1ps
`default_nettype none

`define V1X 63:58
`define V1Y 57:52
`define V1Z 51:46
`define V2X 45:40
`define V2Y 39:34
`define V3X 27:22
`define V3Y 21:16

module rasterize(
      input wire clk,
      input wire rst,
      input wire valid_in,
      input wire [63:0] model_in,

      output logic valid,
      output logic [27:0] pixel_out);

  localparam WAITING = 0;
  localparam RASTERIZE = 1;

  //E_i where indices are A,B,C
  logic signed [6:0] E_1 [2:0];
  logic signed [6:0] E_2 [2:0];
  logic signed [6:0] E_3 [2:0];
  logic signed [5:0] x_1;
  logic signed [5:0] x_2;
  logic signed [5:0] x_3;
  logic signed [5:0] y_1;
  logic signed [5:0] y_2;
  logic signed [5:0] y_3;
  logic signed [5:0] x_min;
  logic signed [5:0] x_max;
  logic signed [5:0] y_min;
  logic signed [5:0] y_max;

  logic signed [8:0] area;

  always_comb begin
    x_1 = $signed(model_in[`V1X]);
    x_2 = $signed(model_in[`V2X]);
    x_3 = $signed(model_in[`V3X]);
    y_1 = $signed(model_in[`V1Y]);
    y_2 = $signed(model_in[`V2Y]);
    y_3 = $signed(model_in[`V3Y]);
            
    x_min = x_1 > x_2 ? (x_2 > x_3 ? x_3: x_1) : (x_1 > x_3 ? x_2 : x_1);
    y_min = y_1 > y_2 ? (y_2 > y_3 ? y_3: y_1) : (y_1 > y_3 ? y_2 : y_3);
    x_max = x_1 > x_2 ? (x_1 > x_3 ? x_1: x_3) : (x_2 > x_3 ? x_2 : x_3);
    y_max = y_1 > y_2 ? (y_1 > y_3 ? y_1: y_3) : (y_2 > y_3 ? y_2 : y_3);
    //e1 uses v1, v2
    E_1[0] = $signed(model_in[`V1Y]) - $signed(model_in[`V2Y]);
    E_1[1] = $signed(model_in[`V2X]) - $signed(model_in[`V1X]);
    E_1[2] = ($signed(model_in[`V1X]) * $signed(model_in[`V2Y])) - ($signed(model_in[`V2X]) * $signed(model_in[`V1Y]));
    //e2 uses v2, v3
    E_2[0] = $signed(model_in[`V2Y]) - $signed(model_in[`V3Y]);
    E_2[1] = $signed(model_in[`V3X]) - $signed(model_in[`V2X]);
    E_2[2] = ($signed(model_in[`V2X]) * $signed(model_in[`V3Y])) - ($signed(model_in[`V3X]) * $signed(model_in[`V2Y]));
    //e3 uses v3, v1
    E_3[0] = $signed(model_in[`V3Y]) - $signed(model_in[`V1Y]);
    E_3[1] = $signed(model_in[`V1X]) - $signed(model_in[`V3X]);
    E_3[2] = ($signed(model_in[`V3X]) * $signed(model_in[`V1Y])) - ($signed(model_in[`V1X]) * $signed(model_in[`V3Y]));

    area = $signed(E_1[2]) + $signed(E_2[2]) + $signed(E_3[2]);
  end

  logic signed [15:0] check_1;
  logic signed [15:0] check_2;
  logic signed [15:0] check_3;
 
  logic [6:0] e1a;
  logic [6:0] e1b;
  logic [6:0] e1c;
 
  always_comb begin
    e1a = E1[0];
    e1b = E1[1];
    e1c = E1[2];
    check_1 = $signed(E1[0])*$signed(x_curr) + $signed(E1[1])*$signed(y_curr) + $signed(E1[2]);
    check_2 = $signed(E2[0])*$signed(x_curr) + $signed(E2[1])*$signed(y_curr) + $signed(E2[2]);
    check_3 = $signed(E3[0])*$signed(x_curr) + $signed(E3[1])*$signed(y_curr) + $signed(E3[2]);
  end

  logic [5:0] x;
  logic [5:0] y;
  always_comb begin
      x = $signed(x_curr) + 'sd32;
      y = $signed(y_curr) + 'sd32;
  end

  logic state;
  logic signed [6:0] E1 [2:0];
  logic signed [6:0] E2 [2:0];
  logic signed [6:0] E3 [2:0];
  logic signed [5:0] x_curr;
  logic signed [5:0] y_curr;
  logic signed [5:0] xmin;
  logic signed [5:0] xmax;
  logic signed [5:0] ymin;
  logic signed [5:0] ymax;
  logic [5:0] z;
  logic [9:0] color;
 
  always_ff @(posedge clk) begin
    if (rst) begin
      state <= 0;
      valid <= 0;
      x_curr <= 0;
      y_curr <= 0;
      xmin <= 0;
      xmax <= 0;
      ymin <= 0;
      ymax <= 0;
      color <= 0;
      z <= 0;
      for (int i=0; i<3; i=i+1) begin
        E1[i] <= 0;
        E2[i] <= 0;
        E3[i] <= 0;
      end
    end else begin
      case (state)
        WAITING: begin
          if (valid_in) begin
            if (area == 0) begin
              //malformed triangle
              state <= WAITING;
            end else if (area < 0) begin
              E1[0] <= (~($signed(E_1[0]))) + 'sd1;
              E1[1] <= (~($signed(E_1[1]))) + 'sd1;
              E1[2] <= (~($signed(E_1[2]))) + 'sd1;
              E2[0] <= (~($signed(E_2[0]))) + 'sd1;
              E2[1] <= (~($signed(E_2[1]))) + 'sd1;
              E2[2] <= (~($signed(E_2[2]))) + 'sd1;
              E3[0] <= (~($signed(E_3[0]))) + 'sd1;
              E3[1] <= (~($signed(E_3[1]))) + 'sd1;
              E3[2] <= (~($signed(E_3[2]))) + 'sd1;
              state <= RASTERIZE;
            end else begin
              E1[0] <= E_1[0];
              E1[1] <= E_1[1];
              E1[2] <= E_1[2];
              E2[0] <= E_2[0];
              E2[1] <= E_2[1];
              E2[2] <= E_2[2];
              E3[0] <= E_3[0];
              E3[1] <= E_3[1];
              E3[2] <= E_3[2];
              state <= RASTERIZE;
            end
            x_curr <= x_min;
            y_curr <= y_min;
            xmin <= x_min;
            xmax <= x_max;
            ymin <= y_min;
            ymax <= y_max;
            z <= model_in[`V1Z];
            color <= model_in[9:0];
          end
          valid <= 0;
        end
        RASTERIZE: begin
          if (check_1 >= 0 && check_2 >= 0 && check_3 >= 0) begin
            valid <= 1;
            pixel_out <= {x, y, z, color};
          end else begin
            valid <= 0;
          end
          if (x_curr == xmax && y_curr == ymax) begin
            state <= WAITING;
          end else if (x_curr == xmax) begin
            x_curr <= xmin;
            y_curr <= $signed(y_curr) + 'sd1;
          end else begin
            x_curr <= $signed(x_curr) + 'sd1;
          end
        end
        default: begin
          state <= WAITING;
        end
      endcase
    end
  end
endmodule


`default_nettype wire

sim/rasterize_tb.sv
`timescale 1ns / 1ps
`default_nettype none

module rasterize_tb;
  logic clk;
  logic rst;

  logic valid_in;
  logic [63:0] model_in;

  logic valid_out;
  logic [27:0] pixel_out;
  /* A quick note about this simulation! Most waveform viewers
   * (including GTKWave) don't display arrays in their output
   * unless the array is packed along all dimensions. This is
   * to prevent the amount of data GTKWave has to render from 
   * getting too large, but it also means you'll have to use
   * $display statements to read out from your arrays.
  */

  rasterize uut (
    .clk(clk),
    .rst(rst),
    .valid_in(valid_in),
    .model_in(model_in),
    .valid(valid_out),
    .pixel_out(pixel_out)
  );

  always begin
    #10;
    clk = !clk;
  end

  initial begin
    $dumpfile("rasterize.vcd");
    $dumpvars(0, rasterize_tb);
    $display("Starting Sim");
    clk = 0;
    rst = 0;
    #20;
    rst = 1;
    #20;
    rst = 0;

    $display("test 1:");
    valid_in = 1;
    model_in = 64'h0410C21000C10003;
    for (int i=0; i<10; i=i+1) begin
      #20;
      valid_in = 0;
      $display("valid out ", valid_out);
      $display("pixel out ", pixel_out);
    end
    #80;

    $display("finishing sim"); 
    $finish;
  end
endmodule //sine_table_tb

`default_nettype wire

rasterize.vcd
$date
	Wed Nov 23 06:12:42 2022
$end
$version
	Icarus Verilog
$end
$timescale
	1ps
$end
$scope module rasterize_tb $end
$var wire 1 ! valid_out $end
$var wire 28 " pixel_out [27:0] $end
$var reg 1 # clk $end
$var reg 64 $ model_in [63:0] $end
$var reg 1 % rst $end
$var reg 1 & valid_in $end
$scope module uut $end
$var wire 1 # clk $end
$var wire 64 ' model_in [63:0] $end
$var wire 1 % rst $end
$var wire 1 & valid_in $end
$var parameter 32 ( RASTERIZE $end
$var parameter 32 ) WAITING $end
$var reg 9 * area [8:0] $end
$var reg 16 + check_1 [15:0] $end
$var reg 16 , check_2 [15:0] $end
$var reg 16 - check_3 [15:0] $end
$var reg 10 . color [9:0] $end
$var reg 7 / e1a [6:0] $end
$var reg 7 0 e1b [6:0] $end
$var reg 7 1 e1c [6:0] $end
$var reg 28 2 pixel_out [27:0] $end
$var reg 1 3 state $end
$var reg 1 ! valid $end
$var reg 6 4 x [5:0] $end
$var reg 6 5 x_1 [5:0] $end
$var reg 6 6 x_2 [5:0] $end
$var reg 6 7 x_3 [5:0] $end
$var reg 6 8 x_curr [5:0] $end
$var reg 6 9 x_max [5:0] $end
$var reg 6 : x_min [5:0] $end
$var reg 6 ; xmax [5:0] $end
$var reg 6 < xmin [5:0] $end
$var reg 6 = y [5:0] $end
$var reg 6 > y_1 [5:0] $end
$var reg 6 ? y_2 [5:0] $end
$var reg 6 @ y_3 [5:0] $end
$var reg 6 A y_curr [5:0] $end
$var reg 6 B y_max [5:0] $end
$var reg 6 C y_min [5:0] $end
$var reg 6 D ymax [5:0] $end
$var reg 6 E ymin [5:0] $end
$var reg 6 F z [5:0] $end
$scope begin $ivl_for_loop1 $end
$var integer 32 G i [31:0] $end
$upscope $end
$upscope $end
$scope begin $ivl_for_loop0 $end
$var integer 32 H i [31:0] $end
$upscope $end
$upscope $end
$enddefinitions $end
$comment Show the parameter values. $end
$dumpall
b0 )
b1 (
$end
#0
$dumpvars
b0 H
b0 G
bx F
bx E
bx D
bx C
bx B
bx A
bx @
bx ?
bx >
bx =
bx <
bx ;
bx :
bx 9
bx 8
bx 7
bx 6
bx 5
bx 4
x3
bx 2
bx 1
bx 0
bx /
bx .
bx -
bx ,
bx +
bx *
bx '
x&
0%
bx $
0#
bx "
x!
$end
#10000
03
1#
#20000
0#
1%
#30000
b100000 =
b100000 4
b0 -
b0 ,
b0 +
b0 1
b0 0
b0 /
b0 F
b0 .
b0 D
b0 E
b0 ;
b0 <
b0 A
b0 8
0!
b11 G
1#
#40000
b111111010 *
b100 B
b11 9
b1 C
b1 :
b1 @
b100 ?
b1 >
b11 7
b10 6
b1 5
0#
b10000010000110000100001000000000000110000010000000000000011 $
b10000010000110000100001000000000000110000010000000000000011 '
1&
0%
#50000
b100001 =
b100001 4
b110 ,
b1111110 1
b1111111 0
b11 /
b11 .
b11 F
b100 D
b1 E
b11 ;
b1 <
b1 A
b1 8
13
1#
#60000
0#
b1 H
0&
#70000
b100010 4
b11 ,
b11 +
b10 8
b1000011000010000110000000011 "
b1000011000010000110000000011 2
1!
1#
#80000
0#
b10 H
#90000
b100011 4
b0 ,
b110 +
b11 8
b1000101000010000110000000011 "
b1000101000010000110000000011 2
1#
#100000
0#
b11 H
#110000
b100010 =
b100001 4
b10 -
b101 ,
b1111111111111111 +
b10 A
b1 8
b1000111000010000110000000011 "
b1000111000010000110000000011 2
1#
#120000
0#
b100 H
#130000
b100010 4
b10 ,
b10 +
b10 8
0!
1#
#140000
0#
b101 H
#150000
b100011 4
b1111111111111111 ,
b101 +
b11 8
b1000101000100000110000000011 "
b1000101000100000110000000011 2
1!
1#
#160000
0#
b110 H
#170000
b100011 =
b100001 4
b100 -
b100 ,
b1111111111111110 +
b11 A
b1 8
0!
1#
#180000
0#
b111 H
#190000
b100010 4
b1 ,
b1 +
b10 8
1#
#200000
0#
b1000 H
#210000
b100011 4
b1111111111111110 ,
b100 +
b11 8
b1000101000110000110000000011 "
b1000101000110000110000000011 2
1!
1#
#220000
0#
b1001 H
#230000
b100100 =
b100001 4
b110 -
b11 ,
b1111111111111101 +
b100 A
b1 8
0!
1#
#240000
0#
b1010 H
#250000
b100010 4
b0 ,
b0 +
b10 8
1#
#260000
0#
#270000
b100011 4
b1111111111111101 ,
b11 +
b11 8
b1000101001000000110000000011 "
b1000101001000000110000000011 2
1!
1#
#280000
0#
#290000
03
0!
1#
